chibi_yum_repo/__init__.py
chibi_yum_repo/repo.py
chibi_yum_repo-0.0.2.dist-info/AUTHORS.rst
chibi_yum_repo-0.0.2.dist-info/LICENSE
chibi_yum_repo-0.0.2.dist-info/METADATA
chibi_yum_repo-0.0.2.dist-info/WHEEL
chibi_yum_repo-0.0.2.dist-info/top_level.txt
chibi_yum_repo-0.0.2.dist-info/RECORD
